{
  "album": [
    {
      "file": "20251227.jpeg",
      "caption": "2歳未勝利　優勝　504kg　2025年12月27日（2歳）",
      "isHero": true
    },
    {
      "file": "20250331.webp",
      "caption": "NF早来　491kg　2025年3月31日（2歳）",
      "isHero": false
    },
    {
      "file": "20250131.jpg",
      "caption": "NF早来　490kg　2025年1月31日（2歳）",
      "isHero": false
    },
    {
      "file": "20241129.webp",
      "caption": "NF早来　494kg　2024年11月29日（1歳）",
      "isHero": false
    },
    {
      "file": "20240930.webp",
      "caption": "NF早来　466kg　2024年9月30日（1歳）",
      "isHero": false
    },
    {
      "file": "20240826.webp",
      "caption": "募集時　460kg　2024年8月26日（1歳）",
      "isHero": false
    }
  ],
  "archiveComment": [
    {
      "date": "YYYY-MM-DD",
      "title": "",
      "text": ""
    }
  ]
}